dfflow/__init__.py
dfflow/cleaning.py
dfflow/decorators.py
dfflow/flow.py
dfflow/logger.py
dfflow/profile.py
dfflow/utils.py
dfflow-0.1.0.dist-info/licenses/LICENSE
tests/__init__.py
tests/test_cleaning.py
tests/test_flow.py
tests/test_logger.py
tests/test_profile.py
dfflow-0.1.0.dist-info/METADATA
dfflow-0.1.0.dist-info/WHEEL
dfflow-0.1.0.dist-info/top_level.txt
dfflow-0.1.0.dist-info/RECORD
