Metadata-Version: 2.4
Name: dfflow
Version: 0.1.0
Summary: Lightweight pandas DataFrame logging and flow tracker
Home-page: https://github.com/suressssz/dfflow
Author: Suresh K
Classifier: Programming Language :: Python :: 3
Classifier: License :: OSI Approved :: MIT License
Classifier: Operating System :: OS Independent
Requires-Python: >=3.7
License-File: LICENSE
Requires-Dist: pandas>=1.3
Dynamic: author
Dynamic: classifier
Dynamic: description
Dynamic: description-content-type
Dynamic: home-page
Dynamic: license-file
Dynamic: requires-dist
Dynamic: requires-python
Dynamic: summary
